checkpoint/__init__.py
checkpoint/app.py
checkpoint/database.py
checkpoint/graph.py
checkpoint/task.py
checkpoint/types.py
checkpoint_tool-0.11.1.dist-info/METADATA
checkpoint_tool-0.11.1.dist-info/WHEEL
checkpoint_tool-0.11.1.dist-info/RECORD
