Metadata-Version: 2.1
Name: checkpoint-tool
Version: 0.11.1
Summary: A lightweight workflow management tool written in pure Python
Home-page: https://github.com/koheimiya/checkpoint
License: MIT
Author: Kohei Miyaguchi
Author-email: koheimiyaguchi@gmail.com
Requires-Python: >=3.10,<4.0
Classifier: License :: OSI Approved :: MIT License
Classifier: Programming Language :: Python :: 3
Classifier: Programming Language :: Python :: 3.10
Classifier: Programming Language :: Python :: 3.11
Requires-Dist: click (>=8.1.3,<9.0.0)
Requires-Dist: cloudpickle (>=2.2.1,<3.0.0)
Requires-Dist: diskcache (>=5.6.1,<6.0.0)
Requires-Dist: networkx (>=3.1,<4.0)
Requires-Dist: tqdm (>=4.65.0,<5.0.0)
Requires-Dist: typing-extensions (>=4.5.0,<5.0.0)
Project-URL: Repository, https://github.com/koheimiya/checkpoint
